odoo/addons/purchase_partner_selectable_option/README.rst
odoo/addons/purchase_partner_selectable_option/__init__.py
odoo/addons/purchase_partner_selectable_option/__manifest__.py
odoo/addons/purchase_partner_selectable_option/data/ir_config_parameter.xml
odoo/addons/purchase_partner_selectable_option/i18n/es.po
odoo/addons/purchase_partner_selectable_option/i18n/it.po
odoo/addons/purchase_partner_selectable_option/i18n/pt_BR.po
odoo/addons/purchase_partner_selectable_option/i18n/purchase_partner_selectable_option.pot
odoo/addons/purchase_partner_selectable_option/models/__init__.py
odoo/addons/purchase_partner_selectable_option/models/purchase_order.py
odoo/addons/purchase_partner_selectable_option/models/res_partner.py
odoo/addons/purchase_partner_selectable_option/readme/CONFIGURE.md
odoo/addons/purchase_partner_selectable_option/readme/CONTRIBUTORS.md
odoo/addons/purchase_partner_selectable_option/readme/DESCRIPTION.md
odoo/addons/purchase_partner_selectable_option/readme/USAGE.md
odoo/addons/purchase_partner_selectable_option/static/description/icon.png
odoo/addons/purchase_partner_selectable_option/static/description/index.html
odoo/addons/purchase_partner_selectable_option/tests/__init__.py
odoo/addons/purchase_partner_selectable_option/tests/test_purchase_partner_selectable_option.py
odoo/addons/purchase_partner_selectable_option/views/res_partner_view.xml
odoo_addon_purchase_partner_selectable_option-18.0.1.0.0.2.dist-info/METADATA
odoo_addon_purchase_partner_selectable_option-18.0.1.0.0.2.dist-info/WHEEL
odoo_addon_purchase_partner_selectable_option-18.0.1.0.0.2.dist-info/top_level.txt
odoo_addon_purchase_partner_selectable_option-18.0.1.0.0.2.dist-info/RECORD
